test_sotto/__init__.py
test_sotto/example.py
test_sotto-0.0.1.dist-info/LICENSE
test_sotto-0.0.1.dist-info/METADATA
test_sotto-0.0.1.dist-info/WHEEL
test_sotto-0.0.1.dist-info/top_level.txt
test_sotto-0.0.1.dist-info/RECORD
