Metadata-Version: 2.1
Name: test-sotto
Version: 0.0.1
Summary: Testing packaging.
Author: sotto
Author-email: sotto@42porto.com
License: MIT License
Project-URL: repository, https://github.com/mlanca-c/test_sotto
Project-URL: Bug Tracker, https://github.com/mlanca-c/test_sotto/issues
Classifier: Programming Language :: Python :: 3
Classifier: License :: OSI Approved :: MIT License
Classifier: Operating System :: OS Independent
Requires-Python: >=3.10
License-File: LICENSE
